justanotherlogger/Logger.py
justanotherlogger/__init__.py
justanotherlogger-0.0.3.dist-info/LICENSE
justanotherlogger-0.0.3.dist-info/METADATA
justanotherlogger-0.0.3.dist-info/WHEEL
justanotherlogger-0.0.3.dist-info/top_level.txt
justanotherlogger-0.0.3.dist-info/RECORD
