Metadata-Version: 2.1
Name: justanotherlogger
Version: 0.0.3
Summary: A very simple logger
Author: RockArtist33
Author-email: RockArtist33 <RockArtist33@proton.me>
Project-URL: Homepage, https://github.com/RockArtist33/JustAnotherLogger.git/
Project-URL: Issues, https://github.com/RockArtist33/JustAnotherLogger.git/issues
Classifier: Programming Language :: Python :: 3
Classifier: License :: OSI Approved :: MIT License
Classifier: Operating System :: OS Independent
Requires-Python: >=3.8
License-File: LICENSE
